CHANGES.rst
MANIFEST.in
README.rst
base.cfg
buildout.cfg
funkload.cfg
setup.py
travis.cfg
docs/CREDITS.txt
docs/LICENSE.txt
src/Products/__init__.py
src/Products.Ploneboard.egg-info/PKG-INFO
src/Products.Ploneboard.egg-info/SOURCES.txt
src/Products.Ploneboard.egg-info/dependency_links.txt
src/Products.Ploneboard.egg-info/entry_points.txt
src/Products.Ploneboard.egg-info/namespace_packages.txt
src/Products.Ploneboard.egg-info/not-zip-safe
src/Products.Ploneboard.egg-info/requires.txt
src/Products.Ploneboard.egg-info/top_level.txt
src/Products/Ploneboard/PloneboardTool.py
src/Products/Ploneboard/TODO.txt
src/Products/Ploneboard/__init__.py
src/Products/Ploneboard/adapters.py
src/Products/Ploneboard/batch.py
src/Products/Ploneboard/catalog.py
src/Products/Ploneboard/config.py
src/Products/Ploneboard/configure.zcml
src/Products/Ploneboard/interfaces.py
src/Products/Ploneboard/permissions.py
src/Products/Ploneboard/po-update
src/Products/Ploneboard/rebuild_i18n.sh
src/Products/Ploneboard/setuphandlers.py
src/Products/Ploneboard/tool.gif
src/Products/Ploneboard/utils.py
src/Products/Ploneboard/vocabulary.py
src/Products/Ploneboard/Extensions/Install.py
src/Products/Ploneboard/Extensions/WorkflowScripts.py
src/Products/Ploneboard/Extensions/__init__.py
src/Products/Ploneboard/browser/__init__.py
src/Products/Ploneboard/browser/board.py
src/Products/Ploneboard/browser/comment.py
src/Products/Ploneboard/browser/configure.zcml
src/Products/Ploneboard/browser/controlpanel.py
src/Products/Ploneboard/browser/events.py
src/Products/Ploneboard/browser/forum.py
src/Products/Ploneboard/browser/interfaces.py
src/Products/Ploneboard/browser/pb_attachment.js
src/Products/Ploneboard/browser/ploneboard.css
src/Products/Ploneboard/browser/rss.pt
src/Products/Ploneboard/browser/rss.py
src/Products/Ploneboard/browser/search.pt
src/Products/Ploneboard/browser/search.py
src/Products/Ploneboard/browser/utils.py
src/Products/Ploneboard/browser/templates/addconversation.pt
src/Products/Ploneboard/browser/templates/board.pt
src/Products/Ploneboard/browser/templates/conversation_view.pt
src/Products/Ploneboard/browser/templates/forum.pt
src/Products/Ploneboard/browser/templates/threaded_conversation_view.pt
src/Products/Ploneboard/content/Ploneboard.py
src/Products/Ploneboard/content/PloneboardComment.py
src/Products/Ploneboard/content/PloneboardConversation.py
