Metadata-Version: 1.1
Name: Products.Ploneboard
Version: 3.6
Summary: A discussion board for Plone.
Home-page: https://github.com/collective/Products.Ploneboard
Author: Jarn, Wichert Akkerman, Martin Aspeli
Author-email: plone-product-developers@lists.plone.org
License: GPL
Keywords: Zope CMF Plone board forum
Platform: UNKNOWN
Classifier: Framework :: Plone
Classifier: Framework :: Plone :: 4.1
Classifier: Framework :: Plone :: 4.2
Classifier: Framework :: Plone :: 4.3
Classifier: Framework :: Zope2
Classifier: Programming Language :: Python
